{
    "image": {
        "address": "/Users/anuradhakumari/Library/Mobile Documents/com~apple~CloudDocs/KAINest/document-extraction-system/dataset/employee_docs/generated_docs/aadhaar/menon_asha_back_19930418_overexposed.png",
        "ground_truth_address": "/Users/anuradhakumari/Library/Mobile Documents/com~apple~CloudDocs/KAINest/document-extraction-system/dataset/employee_docs/ground_truth/aadhaar/menon_asha_back_19930418_overexposed.json",
        "side": "back",
        "quality": "overexposed"
    },
    "ground_truth": {
        "aadhaar_number": "3101 6165 8168",
        "vid": "",
        "relationship_label": "Father",
        "care_of": "",
        "father_name": "Suresh Menon",
        "husband_name": "",
        "hindi_relationship_label": "पिता",
        "hindi_care_of": "",
        "hindi_father_name": "सुरेश मेनन",
        "hindi_husband_name": "",
        "address": "42 MG Road Kochi Kerala 682001",
        "hindi_address": "42 मग रोड कओचइ कएरअलअ 682001",
        "hindi_address_lines": [
            "पता:",
            "पिता: सुरेश मेनन",
            "42, मग रोड",
            "कओचइ, कएरअलअ",
            "682001"
        ],
        "pincode": "682001"
    },
    "models": {
        "easyocr": {
            "extracted_data": {
                "aadhaar_number": "3101 6165 8168",
                "address": "Kochi, Kerala 682001",
                "pincode": "682001",
                "vid": "",
                "relationship_label": "Father",
                "care_of": "",
                "father_name": "Suresh Menon",
                "husband_name": "",
                "hindi_relationship_label": "",
                "hindi_care_of": "",
                "hindi_father_name": "",
                "hindi_husband_name": "",
                "hindi_address": "682001",
                "hindi_address_lines": [
                    "682001"
                ]
            },
            "comparison_with_ground_truth": {
                "accuracy_percent": 55.56,
                "matched_fields": 5,
                "total_fields": 9,
                "fields": {
                    "aadhaar_number": {
                        "expected": "3101 6165 8168",
                        "extracted": "3101 6165 8168",
                        "match": true,
                        "used_for_accuracy": true,
                        "similarity_percent": 100
                    },
                    "vid": {
                        "expected": "",
                        "extracted": "",
                        "match": false,
                        "used_for_accuracy": false,
                        "reason": "ground truth value not present"
                    },
                    "relationship_label": {
                        "expected": "Father",
                        "extracted": "Father",
                        "match": true,
                        "used_for_accuracy": true,
                        "similarity_percent": 100
                    },
                    "care_of": {
                        "expected": "",
                        "extracted": "",
                        "match": false,
                        "used_for_accuracy": false,
                        "reason": "ground truth value not present"
                    },
                    "father_name": {
                        "expected": "Suresh Menon",
                        "extracted": "Suresh Menon",
                        "match": true,
                        "used_for_accuracy": true,
                        "similarity_percent": 100.0
                    },
                    "husband_name": {
                        "expected": "",
                        "extracted": "",
                        "match": false,
                        "used_for_accuracy": false,
                        "reason": "ground truth value not present"
                    },
                    "hindi_relationship_label": {
                        "expected": "पिता",
                        "extracted": "",
                        "match": false,
                        "used_for_accuracy": true,
                        "similarity_percent": 0
                    },
                    "hindi_care_of": {
                        "expected": "",
                        "extracted": "",
                        "match": false,
                        "used_for_accuracy": false,
                        "reason": "ground truth value not present"
                    },
                    "hindi_father_name": {
                        "expected": "सुरेश मेनन",
                        "extracted": "",
                        "match": false,
                        "used_for_accuracy": true,
                        "similarity_percent": 0
                    },
                    "hindi_husband_name": {
                        "expected": "",
                        "extracted": "",
                        "match": false,
                        "used_for_accuracy": false,
                        "reason": "ground truth value not present"
                    },
                    "address": {
                        "expected": "42 MG Road Kochi Kerala 682001",
                        "extracted": "Kochi, Kerala 682001",
                        "match": true,
                        "used_for_accuracy": true,
                        "similarity_percent": 77.55
                    },
                    "hindi_address": {
                        "expected": "42 मग रोड कओचइ कएरअलअ 682001",
                        "extracted": "682001",
                        "match": false,
                        "used_for_accuracy": true,
                        "similarity_percent": 35.29
                    },
                    "hindi_address_lines": {
                        "expected": [
                            "पता:",
                            "पिता: सुरेश मेनन",
                            "42, मग रोड",
                            "कओचइ, कएरअलअ",
                            "682001"
                        ],
                        "extracted": [
                            "682001"
                        ],
                        "match": false,
                        "used_for_accuracy": true,
                        "similarity_percent": 22.22
                    },
                    "pincode": {
                        "expected": "682001",
                        "extracted": "682001",
                        "match": true,
                        "used_for_accuracy": true,
                        "similarity_percent": 100
                    }
                }
            }
        },
        "tesseract": {
            "extracted_data": {
                "aadhaar_number": "3101 6165 8168",
                "address": "682001",
                "pincode": "682001",
                "vid": "",
                "relationship_label": "Father",
                "care_of": "",
                "father_name": "Suresh Menon",
                "husband_name": "",
                "hindi_relationship_label": "पति",
                "hindi_care_of": "",
                "hindi_father_name": "",
                "hindi_husband_name": "सुरेश मेनन",
                "hindi_address": "42, मग रोड Kochi, Kerala कओचड, कएरअलअ 682001",
                "hindi_address_lines": [
                    "पता:",
                    "पति सुरेश मेनन 42, MG Road",
                    "42, मग रोड Kochi, Kerala",
                    "कओचड, कएरअलअ 682001"
                ]
            },
            "comparison_with_ground_truth": {
                "accuracy_percent": 66.67,
                "matched_fields": 6,
                "total_fields": 9,
                "fields": {
                    "aadhaar_number": {
                        "expected": "3101 6165 8168",
                        "extracted": "3101 6165 8168",
                        "match": true,
                        "used_for_accuracy": true,
                        "similarity_percent": 100
                    },
                    "vid": {
                        "expected": "",
                        "extracted": "",
                        "match": false,
                        "used_for_accuracy": false,
                        "reason": "ground truth value not present"
                    },
                    "relationship_label": {
                        "expected": "Father",
                        "extracted": "Father",
                        "match": true,
                        "used_for_accuracy": true,
                        "similarity_percent": 100
                    },
                    "care_of": {
                        "expected": "",
                        "extracted": "",
                        "match": false,
                        "used_for_accuracy": false,
                        "reason": "ground truth value not present"
                    },
                    "father_name": {
                        "expected": "Suresh Menon",
                        "extracted": "Suresh Menon",
                        "match": true,
                        "used_for_accuracy": true,
                        "similarity_percent": 100.0
                    },
                    "husband_name": {
                        "expected": "",
                        "extracted": "",
                        "match": false,
                        "used_for_accuracy": false,
                        "reason": "ground truth value not present"
                    },
                    "hindi_relationship_label": {
                        "expected": "पिता",
                        "extracted": "पति",
                        "match": false,
                        "used_for_accuracy": true,
                        "similarity_percent": 0
                    },
                    "hindi_care_of": {
                        "expected": "",
                        "extracted": "",
                        "match": false,
                        "used_for_accuracy": false,
                        "reason": "ground truth value not present"
                    },
                    "hindi_father_name": {
                        "expected": "सुरेश मेनन",
                        "extracted": "",
                        "match": false,
                        "used_for_accuracy": true,
                        "similarity_percent": 0
                    },
                    "hindi_husband_name": {
                        "expected": "",
                        "extracted": "सुरेश मेनन",
                        "match": false,
                        "used_for_accuracy": false,
                        "reason": "ground truth value not present"
                    },
                    "address": {
                        "expected": "42 MG Road Kochi Kerala 682001",
                        "extracted": "682001",
                        "match": false,
                        "used_for_accuracy": true,
                        "similarity_percent": 33.33
                    },
                    "hindi_address": {
                        "expected": "42 मग रोड कओचइ कएरअलअ 682001",
                        "extracted": "42, मग रोड Kochi, Kerala कओचड, कएरअलअ 682001",
                        "match": true,
                        "used_for_accuracy": true,
                        "similarity_percent": 83.33
                    },
                    "hindi_address_lines": {
                        "expected": [
                            "पता:",
                            "पिता: सुरेश मेनन",
                            "42, मग रोड",
                            "कओचइ, कएरअलअ",
                            "682001"
                        ],
                        "extracted": [
                            "पता:",
                            "पति सुरेश मेनन 42, MG Road",
                            "42, मग रोड Kochi, Kerala",
                            "कओचड, कएरअलअ 682001"
                        ],
                        "match": true,
                        "used_for_accuracy": true,
                        "similarity_percent": 80.0
                    },
                    "pincode": {
                        "expected": "682001",
                        "extracted": "682001",
                        "match": true,
                        "used_for_accuracy": true,
                        "similarity_percent": 100
                    }
                }
            }
        },
        "paddleocr": {
            "extracted_data": {
                "aadhaar_number": "3101 6165 8168",
                "address": "42, MG Road Kochi, Kerala 682001",
                "pincode": "682001",
                "vid": "",
                "relationship_label": "Father",
                "care_of": "",
                "father_name": "Suresh Menon",
                "husband_name": "",
                "hindi_relationship_label": "पति",
                "hindi_care_of": "",
                "hindi_father_name": "",
                "hindi_husband_name": "ा",
                "hindi_address": "682001",
                "hindi_address_lines": [
                    "682001"
                ]
            },
            "comparison_with_ground_truth": {
                "accuracy_percent": 55.56,
                "matched_fields": 5,
                "total_fields": 9,
                "fields": {
                    "aadhaar_number": {
                        "expected": "3101 6165 8168",
                        "extracted": "3101 6165 8168",
                        "match": true,
                        "used_for_accuracy": true,
                        "similarity_percent": 100
                    },
                    "vid": {
                        "expected": "",
                        "extracted": "",
                        "match": false,
                        "used_for_accuracy": false,
                        "reason": "ground truth value not present"
                    },
                    "relationship_label": {
                        "expected": "Father",
                        "extracted": "Father",
                        "match": true,
                        "used_for_accuracy": true,
                        "similarity_percent": 100
                    },
                    "care_of": {
                        "expected": "",
                        "extracted": "",
                        "match": false,
                        "used_for_accuracy": false,
                        "reason": "ground truth value not present"
                    },
                    "father_name": {
                        "expected": "Suresh Menon",
                        "extracted": "Suresh Menon",
                        "match": true,
                        "used_for_accuracy": true,
                        "similarity_percent": 100.0
                    },
                    "husband_name": {
                        "expected": "",
                        "extracted": "",
                        "match": false,
                        "used_for_accuracy": false,
                        "reason": "ground truth value not present"
                    },
                    "hindi_relationship_label": {
                        "expected": "पिता",
                        "extracted": "पति",
                        "match": false,
                        "used_for_accuracy": true,
                        "similarity_percent": 0
                    },
                    "hindi_care_of": {
                        "expected": "",
                        "extracted": "",
                        "match": false,
                        "used_for_accuracy": false,
                        "reason": "ground truth value not present"
                    },
                    "hindi_father_name": {
                        "expected": "सुरेश मेनन",
                        "extracted": "",
                        "match": false,
                        "used_for_accuracy": true,
                        "similarity_percent": 0
                    },
                    "hindi_husband_name": {
                        "expected": "",
                        "extracted": "ा",
                        "match": false,
                        "used_for_accuracy": false,
                        "reason": "ground truth value not present"
                    },
                    "address": {
                        "expected": "42 MG Road Kochi Kerala 682001",
                        "extracted": "42, MG Road Kochi, Kerala 682001",
                        "match": true,
                        "used_for_accuracy": true,
                        "similarity_percent": 100.0
                    },
                    "hindi_address": {
                        "expected": "42 मग रोड कओचइ कएरअलअ 682001",
                        "extracted": "682001",
                        "match": false,
                        "used_for_accuracy": true,
                        "similarity_percent": 35.29
                    },
                    "hindi_address_lines": {
                        "expected": [
                            "पता:",
                            "पिता: सुरेश मेनन",
                            "42, मग रोड",
                            "कओचइ, कएरअलअ",
                            "682001"
                        ],
                        "extracted": [
                            "682001"
                        ],
                        "match": false,
                        "used_for_accuracy": true,
                        "similarity_percent": 22.22
                    },
                    "pincode": {
                        "expected": "682001",
                        "extracted": "682001",
                        "match": true,
                        "used_for_accuracy": true,
                        "similarity_percent": 100
                    }
                }
            }
        }
    }
}